pyteetime/__init__.py
pyteetime/tee-test.py
pyteetime-1.0.0.data/scripts/tee-test.py
pyteetime-1.0.0.dist-info/LICENSE
pyteetime-1.0.0.dist-info/METADATA
pyteetime-1.0.0.dist-info/WHEEL
pyteetime-1.0.0.dist-info/top_level.txt
pyteetime-1.0.0.dist-info/RECORD
