Metadata-Version: 2.1
Name: pyteetime
Version: 1.0.0
Summary: Unix tee command for python
Home-page: http://www.rolf-sander.net/software/pyteetime
Author: Rolf Sander
Author-email: mail@rolf-sander.net
License: UNKNOWN
Platform: UNKNOWN
Classifier: Programming Language :: Python :: 3.6
Classifier: License :: OSI Approved :: GNU General Public License (GPL)
Classifier: Operating System :: Unix
Classifier: Intended Audience :: Developers
Classifier: Natural Language :: English
Classifier: Topic :: System :: Logging
Requires-Python: >=3.6
